{
   "personas":[
      {
         "Nombre":" Pedro ",
         "Apellido":" Guzmán ",
         "DNI":" 22773450 ",
         "Telefono":" 3755121314 ",
         "Localidad":" LN Alem "
      },
      {
         "Nombre":" María ",
         "Apellido":" Nieves ",
         "DNI":" 35928532 ",
         "Telefono":" 3764131517 ",
         "Localidad":" Posadas "
      },
      {
         "Nombre":" Roberto Carlos ",
         "Apellido":" Guerra ",
         "DNI":" 40726384 ",
         "Telefono":" 3758171819 ",
         "Localidad":" Apóstoles "
      },
      {
         "Nombre":" Julieta ",
         "Apellido":" López ",
         "DNI":" 29384710 ",
         "Telefono":" 3751222324 ",
         "Localidad":" Eldorado "
      },
      {
         "Nombre":" Ramón ",
         "Apellido":" Rodríguez ",
         "DNI":" 31749223 ",
         "Telefono":" 3765334455 ",
         "Localidad":" Posadas "
      }
   ]
}